bank_card/__init__.py
bank_card/card.py
bank_card/static.py
bank_card-1.0.5.dist-info/DESCRIPTION.rst
bank_card-1.0.5.dist-info/METADATA
bank_card-1.0.5.dist-info/metadata.json
bank_card-1.0.5.dist-info/RECORD
bank_card-1.0.5.dist-info/top_level.txt
bank_card-1.0.5.dist-info/WHEEL
