Metadata-Version: 2.0
Name: bank-card
Version: 1.0.5
Summary: Get bank card info according to bank card number!
Home-page: https://github.com/xjw0914/bank-card
Author: xjw0914
Author-email: contactxjw@gmail.com
License: apache-2.0
Download-URL: https://github.com/xjw0914/bank-card
Keywords: bank card,python
Platform: UNKNOWN
Classifier: Programming Language :: Python
